AMBER/__init__.py
AMBER/background.py
AMBER/graph_laplacian.py
amber_ds4ms-1.0.1.dist-info/licenses/LICENSE
amber_ds4ms-1.0.1.dist-info/METADATA
amber_ds4ms-1.0.1.dist-info/WHEEL
amber_ds4ms-1.0.1.dist-info/top_level.txt
amber_ds4ms-1.0.1.dist-info/RECORD
